pyqt_tab_widget/__init__.py
pyqt_tab_widget/tabWidget.py
pyqt_tab_widget-0.0.1.dist-info/LICENSE
pyqt_tab_widget-0.0.1.dist-info/METADATA
pyqt_tab_widget-0.0.1.dist-info/WHEEL
pyqt_tab_widget-0.0.1.dist-info/top_level.txt
pyqt_tab_widget-0.0.1.dist-info/RECORD
