Metadata-Version: 2.1
Name: pyqt-tab-widget
Version: 0.0.1
Summary: PyQt QTabWidget which is the most common type. This has a lot of common features such as close a tab, close tabs to the left/right, close other tabs and so on.
Home-page: https://github.com/yjg30737/pyqt-tab-widget.git
Author: Jung Gyu Yoon
Author-email: yjg30737@gmail.com
License: MIT
Platform: UNKNOWN
License-File: LICENSE
Requires-Dist: PyQt5 (>=5.8)
